openpr/__init__.py
openpr-1.2.0.dist-info/DESCRIPTION.rst
openpr-1.2.0.dist-info/METADATA
openpr-1.2.0.dist-info/RECORD
openpr-1.2.0.dist-info/WHEEL
openpr-1.2.0.dist-info/entry_points.txt
openpr-1.2.0.dist-info/metadata.json
openpr-1.2.0.dist-info/top_level.txt
