Metadata-Version: 2.0
Name: openpr
Version: 1.2.0
Summary: Find pull request from given commit hash and open it in a Web browser.
Home-page: https://github.com/yoichi/openpr
Author: Yoichi Nakayama
Author-email: yoichi.nakayama@gmail.com
License: BSD
Platform: UNKNOWN
